quran_phonemizer/__init__.py
quran_phonemizer/constants.py
quran_phonemizer/core.py
quran_phonemizer/db_builder.py
quran_phonemizer/models.py
quran_phonemizer/assets/quran.db
quran_phonemizer/resources/schema.sql
quran_phonemizer-1.0.1.dist-info/METADATA
quran_phonemizer-1.0.1.dist-info/WHEEL
quran_phonemizer-1.0.1.dist-info/licenses/LICENSE
quran_phonemizer-1.0.1.dist-info/RECORD
