Metadata-Version: 2.4
Name: quran-phonemizer
Version: 1.0.1
Summary: Industrial-strength Deterministic Phonemizer for Quranic Arabic (Tajweed-aware)
Project-URL: Homepage, https://github.com/RazwanSiktany/quran-phonemizer
Project-URL: Live Demo, https://quran-phonemizer.streamlit.app/
Project-URL: Source Code, https://github.com/RazwanSiktany/quran-phonemizer
Project-URL: Issue Tracker, https://github.com/RazwanSiktany/quran-phonemizer/issues
Author-email: "Razwan M. Haji" <razwan.siktany778@gmail.com>
License: MIT License
License-File: LICENSE
Keywords: arabic,fastspeech,islamic-ai,nlp,phonemizer,quran,speech-synthesis,tajweed,tts,vits
Classifier: Development Status :: 5 - Production/Stable
Classifier: Intended Audience :: Developers
Classifier: Intended Audience :: Science/Research
Classifier: License :: OSI Approved :: MIT License
Classifier: Operating System :: OS Independent
Classifier: Programming Language :: Python :: 3
Classifier: Programming Language :: Python :: 3.8
Classifier: Programming Language :: Python :: 3.9
Classifier: Programming Language :: Python :: 3.10
Classifier: Programming Language :: Python :: 3.11
Classifier: Programming Language :: Python :: 3.12
Classifier: Topic :: Religion
Classifier: Topic :: Scientific/Engineering :: Artificial Intelligence
Classifier: Topic :: Text Processing :: Linguistic
Requires-Python: >=3.8
Requires-Dist: pydantic>=2.0
Provides-Extra: app
Requires-Dist: streamlit>=1.20.0; extra == 'app'
Provides-Extra: dev
Requires-Dist: build>=0.10.0; extra == 'dev'
Requires-Dist: pytest>=7.0; extra == 'dev'
Requires-Dist: twine>=4.0; extra == 'dev'
